scraper/__init__.py
scraper/command/__init__.py
scraper/command/cli.py
scraper/command/services.py
scraper/debug.py
scraper/extractor.py
scraper/rei.py
scraper/runner.py
scraper/utils/__init__.py
scraper/utils/validation.py
rei_api-0.1.3.dist-info/METADATA
rei_api-0.1.3.dist-info/WHEEL
rei_api-0.1.3.dist-info/RECORD
