Metadata-Version: 2.1
Name: rei-api
Version: 0.1.3
Summary: REI Shop API unofficial with Python
License: MIT
Author: perymerdeka
Author-email: ferilukmansyah@gmail.com
Requires-Python: >=3.11,<4.0
Classifier: License :: OSI Approved :: MIT License
Classifier: Programming Language :: Python :: 3
Classifier: Programming Language :: Python :: 3.11
Classifier: Programming Language :: Python :: 3.12
Requires-Dist: httpx (>=0.25.2,<0.26.0)
Requires-Dist: openpyxl (>=3.1.2,<4.0.0)
Requires-Dist: pandas (>=2.1.4,<3.0.0)
Requires-Dist: rich (>=13.7.0,<14.0.0)
Requires-Dist: selectolax (>=0.3.17,<0.4.0)
